analytics/__init__.py
analytics/ai_analyzer.py
analytics/logging_config.py
analytics/maturity_rubric.py
analytics/survey_analytics.py
blueprints/__init__.py
blueprints/admin_blueprint.py
blueprints/auth_blueprint.py
blueprints/data_blueprint.py
blueprints/health_blueprint.py
blueprints/home_blueprint.py
blueprints/report_blueprint.py
blueprints/summary_blueprint.py
blueprints/api/__init__.py
blueprints/api/admin_edit_api.py
blueprints/api/algorithm_config_api.py
blueprints/api/cache_api.py
blueprints/api/data_api.py
blueprints/api/debug_api.py
blueprints/api/help_api.py
blueprints/api/report_api.py
blueprints/api/stats_api.py
blueprints/api/whats_new_api.py
config/sheet_tabs.py
extractors/__init__.py
extractors/improved_extractor.py
extractors/sheets_reader.py
normalizers/__init__.py
normalizers/survey_normalizer.py
repositories/__init__.py
repositories/admin_edit_repository.py
repositories/qualitative_cache_file_repository.py
repositories/report_repository.py
repositories/sheet_repository.py
repositories/unified_cache_repository.py
services/__init__.py
services/admin_edit_manager.py
services/admin_edit_service.py
services/aggregate_report_builder.py
services/algorithm_config_service.py
services/analytics_service.py
services/auto_sync_service.py
services/build_review_session.py
services/cache_service.py
services/container.py
services/data_importer.py
services/data_service.py
services/data_type_detector.py
services/dimension_analysis_orchestrator.py
services/normalization_orchestrator.py
services/organization_report_builder.py
services/qualitative_cache_repository.py
services/report_data_extractor.py
services/report_generator.py
services/report_service.py
services/schema_manager.py
services/sse_service.py
surveyor/__init__.py
surveyor/cli/__init__.py
surveyor/cli/commands.py
surveyor/cli/main.py
surveyor/config/__init__.py
surveyor/config/container.py
surveyor/config/settings.py
surveyor/models/__init__.py
surveyor/models/base.py
surveyor/models/models.py
jjf_survey_analytics-1.5.3.dist-info/METADATA
jjf_survey_analytics-1.5.3.dist-info/WHEEL
jjf_survey_analytics-1.5.3.dist-info/entry_points.txt
jjf_survey_analytics-1.5.3.dist-info/top_level.txt
jjf_survey_analytics-1.5.3.dist-info/RECORD
