Metadata-Version: 2.4
Name: jjf-survey-analytics
Version: 1.5.3
Summary: A tool for extracting data from Google Sheets and normalizing it into SQLite
Author-email: Your Name <your.email@example.com>
License: MIT
Project-URL: Homepage, https://github.com/bobmatnyc/jjf-survey-analytics
Project-URL: Repository, https://github.com/bobmatnyc/jjf-survey-analytics
Project-URL: Issues, https://github.com/bobmatnyc/jjf-survey-analytics/issues
Keywords: google-sheets,data-extraction,sqlite,cli
Classifier: Development Status :: 3 - Alpha
Classifier: Intended Audience :: Developers
Classifier: License :: OSI Approved :: MIT License
Classifier: Programming Language :: Python :: 3
Classifier: Programming Language :: Python :: 3.13
Classifier: Topic :: Database
Classifier: Topic :: Office/Business :: Financial :: Spreadsheet
Requires-Python: >=3.13
Requires-Dist: click>=8.1.0
Requires-Dist: sqlalchemy>=2.0.0
Requires-Dist: python-dotenv>=1.0.0
Requires-Dist: google-api-python-client>=2.100.0
Requires-Dist: google-auth-httplib2>=0.2.0
Requires-Dist: google-auth-oauthlib>=1.0.0
Requires-Dist: python-dateutil>=2.8.0
Provides-Extra: dev
Requires-Dist: pytest>=7.4.0; extra == "dev"
Requires-Dist: pytest-cov>=4.1.0; extra == "dev"
Requires-Dist: black>=23.0.0; extra == "dev"
Requires-Dist: flake8>=6.0.0; extra == "dev"
Requires-Dist: mypy>=1.5.0; extra == "dev"
